Metadata-Version: 2.1
Name: th2-grpc-data-provider
Version: 1.3.0
Summary: th2_grpc_data_provider
Home-page: https://github.com/th2-net/th2-data-provider
Author: TH2-devs
Author-email: th2-devs@exactprosystems.com
License: Apache License 2.0
Platform: UNKNOWN
Requires-Python: >=3.7
